lessweb/__init__.py
lessweb/annotation.py
lessweb/bridge.py
lessweb/event.py
lessweb/ioc.py
lessweb/py.typed
lessweb/typecast.py
lessweb/utils.py
lessweb-2.2.0.dist-info/licenses/LICENSE.txt
lessweb-2.2.0.dist-info/METADATA
lessweb-2.2.0.dist-info/WHEEL
lessweb-2.2.0.dist-info/top_level.txt
lessweb-2.2.0.dist-info/RECORD
