Metadata-Version: 2.4
Name: lessweb
Version: 2.2.0
Summary: A pythonic web framework
Author-email: qorzj <goodhorsezxj@gmail.com>
License: Copyright lessweb contributors.
Keywords: lessweb,web,web.py,aiohttp
Requires-Python: >=3.10
License-File: LICENSE.txt
Requires-Dist: aiohttp
Requires-Dist: aiojobs
Requires-Dist: toml
Requires-Dist: pyyaml
Requires-Dist: orjson
Requires-Dist: typing_inspect
Requires-Dist: pydantic
Provides-Extra: test
Requires-Dist: flake8; extra == "test"
Requires-Dist: mypy; extra == "test"
Requires-Dist: coverage; extra == "test"
Requires-Dist: pytest; extra == "test"
Requires-Dist: pytest-cov; extra == "test"
Requires-Dist: pytest-mock; extra == "test"
Requires-Dist: pytest-asyncio; extra == "test"
Requires-Dist: pytest-aiohttp; extra == "test"
Requires-Dist: types-toml; extra == "test"
Requires-Dist: types-PyYAML; extra == "test"
Dynamic: license-file
